README.rst
setup.py
fdedup/__init__.py
fdedup/find_duplicates.py
fdedup/iterate_files.py
fdedup/log_count_handler.py
fdedup/main.py
fdedup.egg-info/PKG-INFO
fdedup.egg-info/SOURCES.txt
fdedup.egg-info/dependency_links.txt
fdedup.egg-info/entry_points.txt
fdedup.egg-info/top_level.txt