Metadata-Version: 1.1
Name: fdedup
Version: 0.0.8
Summary: Command line tool to find file duplicates.
Home-page: https://github.com/themalkolm/fdedup
Author: Alexander Krasnukhin, Alexey Ulyanov
Author-email: the.malkom@gmail.com, sibuser.nsk@gmail.com
License: UNKNOWN
Download-URL: https://github.com/themalkolm/fdedup
Keywords: files,duplicates
Platform: UNKNOWN
Classifier: Development Status :: 3 - Alpha
Classifier: Environment :: Console
Classifier: Intended Audience :: End Users/Desktop
Classifier: Operating System :: OS Independent
Classifier: Programming Language :: Python :: 2.7
